{"application_key":"bookverse-platform","version":"2.1.38","created_by":"token:cicd","created_at":"2025-09-12T12:38:11.451Z","tag":"documentation","project_key":"bookverse","status":"COMPLETED","release_status":"RELEASED","service_id":"jfrt@01k3j43gwdv63h17jtb4rx0s9r","application_version_sha256":"afd418864e88a4161dfc554d7e69cb9e4ba8526da35e8db79f5fcb93a9813749","current_stage":"PROD","releasables_count":13,"artifacts_count":80,"total_size":398776213,"releasables":[{"name":"checkout","version":"12-1","package_type":"docker","releasable_type":"package_version","sha256":"0264450d546ea8a57b80f3ced5b1eada8ae4a89fdd2cfd504ff1652b72c02b7f","total_size":74883216,"sources":[{"type":"release_bundle","release_bundle":{"name":"bookverse-web","version":"5.48.34","repo_key":"bookverse-release-bundles-v2"}}]},{"name":"checkout-migrations","version":"12-1","package_type":"docker","releasable_type":"package_version","sha256":"1747dece94917ce1b0256ecd60138ce4deaea1bd35dcb6b2e8afe697dd2f5b71","total_size":3418694,"sources":[{"type":"release_bundle","release_bundle":{"name":"bookverse-web","version":"5.48.34","repo_key":"bookverse-release-bundles-v2"}}]},{"name":"checkout-worker","version":"12-1","package_type":"docker","releasable_type":"package_version","sha256":"0ac7fafba2dfeb14fe9f7b5eeb986a9c4a6e3194af825988308e532de79754f2","total_size":74865652,"sources":[{"type":"release_bundle","release_bundle":{"name":"bookverse-web","version":"5.48.34","repo_key":"bookverse-release-bundles-v2"}}]},{"name":"inventory","version":"20-1","package_type":"docker","releasable_type":"package_version","sha256":"11b89692b2085631f6e2407edd8545b033c8e6945837103875d6db484e945b6f","total_size":83095894,"sources":[{"type":"release_bundle","release_bundle":{"name":"bookverse-web","version":"5.48.34","repo_key":"bookverse-release-bundles-v2"}}]},{"name":"openapi.json","version":"","package_type":"generic","releasable_type":"artifact","sha256":"df7c16eaabd64fe8eb021f122f1e5d304eadb823468fddb0f56795be3a26cb6f","total_size":4787,"sources":[{"type":"release_bundle","release_bundle":{"name":"bookverse-web","version":"5.48.34","repo_key":"bookverse-release-bundles-v2"}}]},{"name":"order.created.schema.json","version":"","package_type":"generic","releasable_type":"artifact","sha256":"56e78f83fe5ef57d6c8348fd56ad223f45affb7bd6abe6663f1b1df1da1f1035","total_size":849,"sources":[{"type":"release_bundle","release_bundle":{"name":"bookverse-web","version":"5.48.34","repo_key":"bookverse-release-bundles-v2"}}]},{"name":"recommendations","version":"13-1","package_type":"docker","releasable_type":"package_version","sha256":"11b2c7ded65133b714fb4eb0bcff347a69bd24689a632a944fde19eff4d92bbf","total_size":69047280,"sources":[{"type":"release_bundle","release_bundle":{"name":"bookverse-web","version":"5.48.34","repo_key":"bookverse-release-bundles-v2"}}]},{"name":"recommendations-config-13-1.tar.gz","version":"","package_type":"generic","releasable_type":"artifact","sha256":"63e67f7a69fe27ff94f54535b0fcda0e10789b8dd414582b6c32da6522f11fdf","total_size":462,"sources":[{"type":"release_bundle","release_bundle":{"name":"bookverse-web","version":"5.48.34","repo_key":"bookverse-release-bundles-v2"}}]},{"name":"recommendations-resources-13-1.tar.gz","version":"","package_type":"generic","releasable_type":"artifact","sha256":"3142dd6e7b54dff56200adda23697d9817644285f3fe7ffde31a78635e7bfa44","total_size":189,"sources":[{"type":"release_bundle","release_bundle":{"name":"bookverse-web","version":"5.48.34","repo_key":"bookverse-release-bundles-v2"}}]},{"name":"recommendations-worker","version":"13-1","package_type":"docker","releasable_type":"package_version","sha256":"11b2c7ded65133b714fb4eb0bcff347a69bd24689a632a944fde19eff4d92bbf","total_size":69047039,"sources":[{"type":"release_bundle","release_bundle":{"name":"bookverse-web","version":"5.48.34","repo_key":"bookverse-release-bundles-v2"}}]},{"name":"sha256__1747dece94917ce1b0256ecd60138ce4deaea1bd35dcb6b2e8afe697dd2f5b71","version":"","package_type":"docker","releasable_type":"artifact","sha256":"1747dece94917ce1b0256ecd60138ce4deaea1bd35dcb6b2e8afe697dd2f5b71","total_size":3415528,"sources":[{"type":"release_bundle","release_bundle":{"name":"bookverse-web","version":"5.48.34","repo_key":"bookverse-release-bundles-v2"}}]},{"name":"web","version":"18-1","package_type":"docker","releasable_type":"package_version","sha256":"0030c60a5d4a969c9b79400f1aaccd7cff29e08d2327356fdfd396dde78684d9","total_size":20986774,"sources":[{"type":"release_bundle","release_bundle":{"name":"bookverse-web","version":"5.48.34","repo_key":"bookverse-release-bundles-v2"}}]},{"name":"web-assets-5.48.34.tar.gz","version":"","package_type":"generic","releasable_type":"artifact","sha256":"97dd5f9d2714729c376b5293c4a35f662b33b86d1d64409250827391e8c17cd0","total_size":9849,"sources":[{"type":"release_bundle","release_bundle":{"name":"bookverse-web","version":"5.48.34","repo_key":"bookverse-release-bundles-v2"}}]}],"sources":[{"type":"release_bundle","release_bundle":{"name":"bookverse-inventory","version":"5.32.55","repo_key":"bookverse-release-bundles-v2"}},{"type":"release_bundle","release_bundle":{"name":"bookverse-recommendations","version":"1.1.30","repo_key":"bookverse-release-bundles-v2"}},{"type":"release_bundle","release_bundle":{"name":"bookverse-checkout","version":"2.38.17","repo_key":"bookverse-release-bundles-v2"}},{"type":"release_bundle","release_bundle":{"name":"bookverse-web","version":"5.48.34","repo_key":"bookverse-release-bundles-v2"}}],"total":13,"limit":100,"offset":0}